py.typed
orq_poc_python_multi_env_version/__init__.py
orq_poc_python_multi_env_version/_hooks/__init__.py
orq_poc_python_multi_env_version/_hooks/registration.py
orq_poc_python_multi_env_version/_hooks/sdkhooks.py
orq_poc_python_multi_env_version/_hooks/types.py
orq_poc_python_multi_env_version/_version.py
orq_poc_python_multi_env_version/basesdk.py
orq_poc_python_multi_env_version/contacts.py
orq_poc_python_multi_env_version/deployments_sdk.py
orq_poc_python_multi_env_version/feedback.py
orq_poc_python_multi_env_version/files.py
orq_poc_python_multi_env_version/httpclient.py
orq_poc_python_multi_env_version/metrics.py
orq_poc_python_multi_env_version/models/__init__.py
orq_poc_python_multi_env_version/models/apierror.py
orq_poc_python_multi_env_version/models/bulkfileuploadop.py
orq_poc_python_multi_env_version/models/createcontactop.py
orq_poc_python_multi_env_version/models/createfeedbackop.py
orq_poc_python_multi_env_version/models/createpromptop.py
orq_poc_python_multi_env_version/models/createpromptversionop.py
orq_poc_python_multi_env_version/models/deletepromptop.py
orq_poc_python_multi_env_version/models/deploymentcreatemetricop.py
orq_poc_python_multi_env_version/models/deploymentgetconfigop.py
orq_poc_python_multi_env_version/models/deploymentinvokeop.py
orq_poc_python_multi_env_version/models/deployments.py
orq_poc_python_multi_env_version/models/deploymentsop.py
orq_poc_python_multi_env_version/models/duplicatepromptop.py
orq_poc_python_multi_env_version/models/fileuploadop.py
orq_poc_python_multi_env_version/models/findonepromptsnippetop.py
orq_poc_python_multi_env_version/models/getallpromptsop.py
orq_poc_python_multi_env_version/models/getallprompttemplatesop.py
orq_poc_python_multi_env_version/models/getonepromptop.py
orq_poc_python_multi_env_version/models/honoapierror.py
orq_poc_python_multi_env_version/models/invaliddeploymentop.py
orq_poc_python_multi_env_version/models/remoteconfigsgetconfigop.py
orq_poc_python_multi_env_version-1.43.3.dist-info/METADATA
orq_poc_python_multi_env_version-1.43.3.dist-info/WHEEL
orq_poc_python_multi_env_version-1.43.3.dist-info/RECORD
